{
    "Host": [
        "Tina Fey",
        "Amy Poehler"
    ],
    "best actor drama for film": {
        "Nominees": [
            "naomi watts",
            "jessica chastain",
            "daniel daylewis"
        ],
        "Presenters": [],
        "Winner": "daniel daylewis"
    },
    "best actor for tv series drama": {
        "Nominees": [
            "damian lewis",
            "jon hamm",
            "bryan cranston"
        ],
        "Presenters": [],
        "Winner": "damian lewis"
    },
    "best actor in a miniseries or tv movie": {
        "Nominees": [
            "benedict cumberbatch",
            "kevin costner",
            "taylor swift"
        ],
        "Presenters": [],
        "Winner": "kevin costner"
    },
    "best actor in a motion picture comedy or musical": {
        "Nominees": [
            "bradley cooper",
            "hugh jackman"
        ],
        "Presenters": [],
        "Winner": "hugh jackman"
    },
    "best actor in a motion picture drama": {
        "Nominees": [
            "naomi watts",
            "jessica chastain",
            "daniel daylewis"
        ],
        "Presenters": [],
        "Winner": "daniel daylewis"
    },
    "best actor musical or comedy": {
        "Nominees": [
            "hugh jackman",
            "bradley cooper",
            "bill murray",
            "jack black"
        ],
        "Presenters": [],
        "Winner": "hugh jackman"
    },
    "best actor tv series comedy or musical": {
        "Nominees": [
            "jim parsons",
            "quentin tarantino",
            "matt leblanc",
            "don cheadle"
        ],
        "Presenters": [],
        "Winner": "don cheadle"
    },
    "best actress drama": {
        "Nominees": [
            "jessica chastain",
            "naomi watts"
        ],
        "Presenters": [],
        "Winner": "jessica chastain"
    },
    "best actress for comedy or musical": {
        "Nominees": [
            "meryl streep",
            "jennifer lawrence",
            "will ferrell"
        ],
        "Presenters": [],
        "Winner": "jennifer lawrence"
    },
    "best actress in a miniseries or tv movie": {
        "Nominees": [
            "julianne moore",
            "jessica lange"
        ],
        "Presenters": [],
        "Winner": "julianne moore"
    },
    "best actress in a tv series comedy or musical": {
        "Nominees": [
            "lena dunham",
            "amy poehler"
        ],
        "Presenters": [],
        "Winner": "lena dunham"
    },
    "best actress motion picture drama": {
        "Nominees": [
            "jessica chastain",
            "naomi watts"
        ],
        "Presenters": [],
        "Winner": "jessica chastain"
    },
    "best actress tv series drama": {
        "Nominees": [
            "claire danes",
            "connie britton",
            "michelle dockery"
        ],
        "Presenters": [],
        "Winner": "claire danes"
    },
    "best animated feature film": {
        "Nominees": [
            "brave",
            "frankenweenie"
        ],
        "Presenters": [
            "sacha baron cohen"
        ],
        "Winner": "brave"
    },
    "best comedy or musical": {
        "Nominees": [
            "silver linings playbook",
            "girls"
        ],
        "Presenters": [],
        "Winner": "girls"
    },
    "best director motion picture": {
        "Nominees": [
            "ben affleck",
            "steven spielberg"
        ],
        "Presenters": [],
        "Winner": "ben affleck"
    },
    "best drama tv series": {
        "Nominees": [
            "skyfall",
            "life of pi",
            "homeland"
        ],
        "Presenters": [],
        "Winner": "homeland"
    },
    "best foreign language film": {
        "Nominees": [
            "amour"
        ],
        "Presenters": [
            "arnold schwarzenegger",
            "sylvester stallone"
        ],
        "Winner": "amour"
    },
    "best miniseries or tv movie": {
        "Nominees": [
            "game change"
        ],
        "Presenters": [],
        "Winner": "game change"
    },
    "best motion picture comedy or musical": {
        "Nominees": [
            "silver linings playbook",
            "les miserables"
        ],
        "Presenters": [],
        "Winner": "les miserables"
    },
    "best motion picture drama": {
        "Nominees": [
            "argo",
            "lincoln",
            "zero dark thirty",
            "it"
        ],
        "Presenters": [],
        "Winner": "argo"
    },
    "best motion picture screenplay": {
        "Nominees": [
            "skyfall",
            "django unchained"
        ],
        "Presenters": [],
        "Winner": "django unchained"
    },
    "best original score": {
        "Nominees": [
            "skyfall",
            "life of pi",
            "homeland",
            "it",
            "her"
        ],
        "Presenters": [],
        "Winner": "life of pi"
    },
    "best original song motion picture": {
        "Nominees": [
            "thank god taylor swift",
            "the for a night out",
            "adele for skyfall",
            "that adele",
            "les mis",
            "skyfall"
        ],
        "Presenters": [],
        "Winner": "skyfall"
    },
    "best performance by an actress in a motion picture drama": {
        "Nominees": [
            "jessica chastain",
            "naomi watts"
        ],
        "Presenters": [],
        "Winner": "jessica chastain"
    },
    "best supporting actor in tv series": {
        "Nominees": [
            "anne hathaway",
            "ed harris",
            "mandy patinkin",
            "meryl streep"
        ],
        "Presenters": [],
        "Winner": "ed harris"
    },
    "best supporting actor motion picture": {
        "Nominees": [
            "christoph waltz",
            "maggie smith",
            "sarah paulson"
        ],
        "Presenters": [],
        "Winner": "christoph waltz"
    },
    "best supporting actress motion picture": {
        "Nominees": [
            "anne hathaway",
            "mandy patinkin",
            "adele"
        ],
        "Presenters": [],
        "Winner": "anne hathaway"
    },
    "best supporting actress tv series miniseries or tv movie": {
        "Nominees": [
            "maggie smith",
            "sarah paulson"
        ],
        "Presenters": [],
        "Winner": "maggie smith"
    },
    "best tv series comedy or musical": {
        "Nominees": [
            "girls",
            "modern family"
        ],
        "Presenters": [],
        "Winner": "girls"
    }
}